{
  "blockRange": {
    "network": "polygon",
    "startBlock": "75417061n",
    "endBlock": "75697434n"
  },
  "poolId": "0x9a005a0c12cc2ef01b34e9a7f3fb91a0e6304d377b5479bd3f08f8c29cdf5deb",
  "positions": [
    [
      "15863n",
      {
        "lastOwner": "0xa2DFeb674d997b68ec5adB0A6fb9136BD45C2D2d",
        "tickLower": -242700,
        "tickUpper": -239760,
        "liquidity": "42675289859n",
        "feeGrowthInsidePeriod0": "0n",
        "feeGrowthInsidePeriod1": "0n",
        "liquidityModifications": [
          {
            "blockNumber": "75417061n",
            "newLiquidityAmount": "42675289859n",
            "owner": "0xa2DFeb674d997b68ec5adB0A6fb9136BD45C2D2d"
          },
          {
            "blockNumber": "75697434n",
            "newLiquidityAmount": "42675289859n",
            "owner": "0xa2DFeb674d997b68ec5adB0A6fb9136BD45C2D2d"
          }
        ],
        "poolId": "0x9a005a0c12cc2ef01b34e9a7f3fb91a0e6304d377b5479bd3f08f8c29cdf5deb"
      }
    ],
    [
      "22442n",
      {
        "lastOwner": "0x40f81795f44b96BF88E16E055f2283B9cAEd9466",
        "tickLower": -240780,
        "tickUpper": -232080,
        "liquidity": "0n",
        "feeGrowthInsidePeriod0": "52275735517564881n",
        "feeGrowthInsidePeriod1": "2092665n",
        "liquidityModifications": [
          {
            "blockNumber": "75417061n",
            "newLiquidityAmount": "13406112901200n",
            "owner": "0x40f81795f44b96BF88E16E055f2283B9cAEd9466"
          },
          {
            "blockNumber": "75450569n",
            "newLiquidityAmount": "13406112901200n",
            "owner": "0x40f81795f44b96BF88E16E055f2283B9cAEd9466"
          },
          {
            "blockNumber": "75450582n",
            "newLiquidityAmount": "0n",
            "owner": "0x40f81795f44b96BF88E16E055f2283B9cAEd9466"
          },
          {
            "blockNumber": "75697434n",
            "newLiquidityAmount": "0n",
            "owner": "0x40f81795f44b96BF88E16E055f2283B9cAEd9466"
          }
        ],
        "poolId": "0x9a005a0c12cc2ef01b34e9a7f3fb91a0e6304d377b5479bd3f08f8c29cdf5deb"
      }
    ],
    [
      "22760n",
      {
        "lastOwner": "0x40f81795f44b96BF88E16E055f2283B9cAEd9466",
        "tickLower": -238260,
        "tickUpper": -228420,
        "liquidity": "1957768445623n",
        "feeGrowthInsidePeriod0": "251196382331228n",
        "feeGrowthInsidePeriod1": "23981n",
        "liquidityModifications": [
          {
            "blockNumber": "75417061n",
            "newLiquidityAmount": "1957768445623n",
            "owner": "0x40f81795f44b96BF88E16E055f2283B9cAEd9466"
          },
          {
            "blockNumber": "75697434n",
            "newLiquidityAmount": "1957768445623n",
            "owner": "0x40f81795f44b96BF88E16E055f2283B9cAEd9466"
          }
        ],
        "poolId": "0x9a005a0c12cc2ef01b34e9a7f3fb91a0e6304d377b5479bd3f08f8c29cdf5deb"
      }
    ],
    [
      "36440n",
      {
        "lastOwner": "0xEf2CD02960bd303C000C48C6ea95f651CfB83205",
        "tickLower": -237300,
        "tickUpper": -230100,
        "liquidity": "11711597711276n",
        "feeGrowthInsidePeriod0": "1502685868172247n",
        "feeGrowthInsidePeriod1": "143461n",
        "liquidityModifications": [
          {
            "blockNumber": "75417061n",
            "newLiquidityAmount": "11711597711276n",
            "owner": "0xEf2CD02960bd303C000C48C6ea95f651CfB83205"
          },
          {
            "blockNumber": "75697434n",
            "newLiquidityAmount": "11711597711276n",
            "owner": "0xEf2CD02960bd303C000C48C6ea95f651CfB83205"
          }
        ],
        "poolId": "0x9a005a0c12cc2ef01b34e9a7f3fb91a0e6304d377b5479bd3f08f8c29cdf5deb"
      }
    ],
    [
      "36445n",
      {
        "lastOwner": "0xCDA0c8a5f22565ae0efB889E5dBb6CE60498d0b4",
        "tickLower": -246360,
        "tickUpper": -232980,
        "liquidity": "60913685591786n",
        "feeGrowthInsidePeriod0": "0n",
        "feeGrowthInsidePeriod1": "0n",
        "liquidityModifications": [
          {
            "blockNumber": "75417061n",
            "newLiquidityAmount": "60913685591786n",
            "owner": "0xCDA0c8a5f22565ae0efB889E5dBb6CE60498d0b4"
          },
          {
            "blockNumber": "75697434n",
            "newLiquidityAmount": "60913685591786n",
            "owner": "0xCDA0c8a5f22565ae0efB889E5dBb6CE60498d0b4"
          }
        ],
        "poolId": "0x9a005a0c12cc2ef01b34e9a7f3fb91a0e6304d377b5479bd3f08f8c29cdf5deb"
      }
    ],
    [
      "36546n",
      {
        "lastOwner": "0x5196E6ff6b95536874ba6405c11f465e026099e0",
        "tickLower": -887220,
        "tickUpper": 887220,
        "liquidity": "917199286n",
        "feeGrowthInsidePeriod0": "117683550899n",
        "feeGrowthInsidePeriod1": "11n",
        "liquidityModifications": [
          {
            "blockNumber": "75417061n",
            "newLiquidityAmount": "917199286n",
            "owner": "0x5196E6ff6b95536874ba6405c11f465e026099e0"
          },
          {
            "blockNumber": "75697434n",
            "newLiquidityAmount": "917199286n",
            "owner": "0x5196E6ff6b95536874ba6405c11f465e026099e0"
          }
        ],
        "poolId": "0x9a005a0c12cc2ef01b34e9a7f3fb91a0e6304d377b5479bd3f08f8c29cdf5deb"
      }
    ],
    [
      "36809n",
      {
        "lastOwner": "0x93Cf0a22a26895650A8AaE960Bf85a01ec6A551C",
        "tickLower": -237240,
        "tickUpper": -233700,
        "liquidity": "0n",
        "feeGrowthInsidePeriod0": "7404236212824009n",
        "feeGrowthInsidePeriod1": "619128n",
        "liquidityModifications": [
          {
            "blockNumber": "75417061n",
            "newLiquidityAmount": "75384649748169n",
            "owner": "0x93Cf0a22a26895650A8AaE960Bf85a01ec6A551C"
          },
          {
            "blockNumber": "75444924n",
            "newLiquidityAmount": "0n",
            "owner": "0x93Cf0a22a26895650A8AaE960Bf85a01ec6A551C"
          },
          {
            "blockNumber": "75697434n",
            "newLiquidityAmount": "0n",
            "owner": "0x93Cf0a22a26895650A8AaE960Bf85a01ec6A551C"
          }
        ],
        "poolId": "0x9a005a0c12cc2ef01b34e9a7f3fb91a0e6304d377b5479bd3f08f8c29cdf5deb"
      }
    ],
    [
      "37150n",
      {
        "lastOwner": "0x0AB4F882E219A33fcE9252b6213aD1146d4354d9",
        "tickLower": -238920,
        "tickUpper": -232500,
        "liquidity": "0n",
        "feeGrowthInsidePeriod0": "55945075689274683n",
        "feeGrowthInsidePeriod1": "3356318n",
        "liquidityModifications": [
          {
            "blockNumber": "75417061n",
            "newLiquidityAmount": "17218786665435n",
            "owner": "0x0AB4F882E219A33fcE9252b6213aD1146d4354d9"
          },
          {
            "blockNumber": "75567175n",
            "newLiquidityAmount": "0n",
            "owner": "0x0AB4F882E219A33fcE9252b6213aD1146d4354d9"
          },
          {
            "blockNumber": "75697434n",
            "newLiquidityAmount": "0n",
            "owner": "0x0AB4F882E219A33fcE9252b6213aD1146d4354d9"
          }
        ],
        "poolId": "0x9a005a0c12cc2ef01b34e9a7f3fb91a0e6304d377b5479bd3f08f8c29cdf5deb"
      }
    ],
    [
      "38005n",
      {
        "lastOwner": "0xa614A83132a2e7368aDa71dA9331817c33706770",
        "tickLower": -234540,
        "tickUpper": -231840,
        "liquidity": "0n",
        "feeGrowthInsidePeriod0": "199951671736510n",
        "feeGrowthInsidePeriod1": "20806n",
        "liquidityModifications": [
          {
            "blockNumber": "75417061n",
            "newLiquidityAmount": "16837171401033n",
            "owner": "0xa614A83132a2e7368aDa71dA9331817c33706770"
          },
          {
            "blockNumber": "75455364n",
            "newLiquidityAmount": "0n",
            "owner": "0xa614A83132a2e7368aDa71dA9331817c33706770"
          },
          {
            "blockNumber": "75697434n",
            "newLiquidityAmount": "0n",
            "owner": "0xa614A83132a2e7368aDa71dA9331817c33706770"
          }
        ],
        "poolId": "0x9a005a0c12cc2ef01b34e9a7f3fb91a0e6304d377b5479bd3f08f8c29cdf5deb"
      }
    ],
    [
      "38055n",
      {
        "lastOwner": "0xabF76381Ab5538598AA4cd77d01De16c3F48a54A",
        "tickLower": -887220,
        "tickUpper": 887220,
        "liquidity": "3819312130280n",
        "feeGrowthInsidePeriod0": "490046405776458n",
        "feeGrowthInsidePeriod1": "46784n",
        "liquidityModifications": [
          {
            "blockNumber": "75417061n",
            "newLiquidityAmount": "3819312130280n",
            "owner": "0xabF76381Ab5538598AA4cd77d01De16c3F48a54A"
          },
          {
            "blockNumber": "75697434n",
            "newLiquidityAmount": "3819312130280n",
            "owner": "0xabF76381Ab5538598AA4cd77d01De16c3F48a54A"
          }
        ],
        "poolId": "0x9a005a0c12cc2ef01b34e9a7f3fb91a0e6304d377b5479bd3f08f8c29cdf5deb"
      }
    ],
    [
      "38210n",
      {
        "lastOwner": "0xD98b537374623B2cFc2f083fcE50b525A697A6b7",
        "tickLower": -253260,
        "tickUpper": -230220,
        "liquidity": "1232983959065588n",
        "feeGrowthInsidePeriod0": "158201094047744899n",
        "feeGrowthInsidePeriod1": "15103512n",
        "liquidityModifications": [
          {
            "blockNumber": "75417061n",
            "newLiquidityAmount": "1232983959065588n",
            "owner": "0xD98b537374623B2cFc2f083fcE50b525A697A6b7"
          },
          {
            "blockNumber": "75697434n",
            "newLiquidityAmount": "1232983959065588n",
            "owner": "0xD98b537374623B2cFc2f083fcE50b525A697A6b7"
          }
        ],
        "poolId": "0x9a005a0c12cc2ef01b34e9a7f3fb91a0e6304d377b5479bd3f08f8c29cdf5deb"
      }
    ],
    [
      "38216n",
      {
        "lastOwner": "0xBa2ACC7b677dd133F8B6e5cEde8ea7Fd9C1c6795",
        "tickLower": -253320,
        "tickUpper": -230280,
        "liquidity": "122319244916725n",
        "feeGrowthInsidePeriod0": "15694476985398140n",
        "feeGrowthInsidePeriod1": "1498357n",
        "liquidityModifications": [
          {
            "blockNumber": "75417061n",
            "newLiquidityAmount": "122319244916725n",
            "owner": "0xBa2ACC7b677dd133F8B6e5cEde8ea7Fd9C1c6795"
          },
          {
            "blockNumber": "75697434n",
            "newLiquidityAmount": "122319244916725n",
            "owner": "0xBa2ACC7b677dd133F8B6e5cEde8ea7Fd9C1c6795"
          }
        ],
        "poolId": "0x9a005a0c12cc2ef01b34e9a7f3fb91a0e6304d377b5479bd3f08f8c29cdf5deb"
      }
    ],
    [
      "38261n",
      {
        "lastOwner": "0xca279F34640B8E3232aBD83951169Be9414CDfda",
        "tickLower": -234540,
        "tickUpper": -231000,
        "liquidity": "104789531107671n",
        "feeGrowthInsidePeriod0": "13330252385350616n",
        "feeGrowthInsidePeriod1": "1272894n",
        "liquidityModifications": [
          {
            "blockNumber": "75417061n",
            "newLiquidityAmount": "104789531107671n",
            "owner": "0xca279F34640B8E3232aBD83951169Be9414CDfda"
          },
          {
            "blockNumber": "75697434n",
            "newLiquidityAmount": "104789531107671n",
            "owner": "0xca279F34640B8E3232aBD83951169Be9414CDfda"
          }
        ],
        "poolId": "0x9a005a0c12cc2ef01b34e9a7f3fb91a0e6304d377b5479bd3f08f8c29cdf5deb"
      }
    ],
    [
      "38336n",
      {
        "lastOwner": "0xca279F34640B8E3232aBD83951169Be9414CDfda",
        "tickLower": -235200,
        "tickUpper": -231060,
        "liquidity": "126570437030529n",
        "feeGrowthInsidePeriod0": "15982321268533995n",
        "feeGrowthInsidePeriod1": "1526471n",
        "liquidityModifications": [
          {
            "blockNumber": "75417061n",
            "newLiquidityAmount": "126570437030529n",
            "owner": "0xca279F34640B8E3232aBD83951169Be9414CDfda"
          },
          {
            "blockNumber": "75697434n",
            "newLiquidityAmount": "126570437030529n",
            "owner": "0xca279F34640B8E3232aBD83951169Be9414CDfda"
          }
        ],
        "poolId": "0x9a005a0c12cc2ef01b34e9a7f3fb91a0e6304d377b5479bd3f08f8c29cdf5deb"
      }
    ],
    [
      "38662n",
      {
        "lastOwner": "0xD12eabdDA283287cBe21EB1DaAdff5110B44be03",
        "tickLower": -887220,
        "tickUpper": 887220,
        "liquidity": "169696005910220n",
        "feeGrowthInsidePeriod0": "21773270927932099n",
        "feeGrowthInsidePeriod1": "2078701n",
        "liquidityModifications": [
          {
            "blockNumber": "75417061n",
            "newLiquidityAmount": "169696005910220n",
            "owner": "0xE6A50d73a5276a5A7Ecb467538C4E5907a1Ae20a"
          },
          {
            "blockNumber": "75697434n",
            "newLiquidityAmount": "169696005910220n",
            "owner": "0xD12eabdDA283287cBe21EB1DaAdff5110B44be03"
          }
        ],
        "poolId": "0x9a005a0c12cc2ef01b34e9a7f3fb91a0e6304d377b5479bd3f08f8c29cdf5deb"
      }
    ],
    [
      "38892n",
      {
        "lastOwner": "0xf31cac93488D5C687C7CbCd58e3ea11609D7dD08",
        "tickLower": -234600,
        "tickUpper": -231660,
        "liquidity": "0n",
        "feeGrowthInsidePeriod0": "929927188069446n",
        "feeGrowthInsidePeriod1": "94275n",
        "liquidityModifications": [
          {
            "blockNumber": "75417061n",
            "newLiquidityAmount": "26215041472538n",
            "owner": "0xf31cac93488D5C687C7CbCd58e3ea11609D7dD08"
          },
          {
            "blockNumber": "75436976n",
            "newLiquidityAmount": "26215041472538n",
            "owner": "0xf31cac93488D5C687C7CbCd58e3ea11609D7dD08"
          },
          {
            "blockNumber": "75535046n",
            "newLiquidityAmount": "26215041472538n",
            "owner": "0xf31cac93488D5C687C7CbCd58e3ea11609D7dD08"
          },
          {
            "blockNumber": "75631237n",
            "newLiquidityAmount": "26215041472538n",
            "owner": "0xf31cac93488D5C687C7CbCd58e3ea11609D7dD08"
          },
          {
            "blockNumber": "75631282n",
            "newLiquidityAmount": "0n",
            "owner": "0xf31cac93488D5C687C7CbCd58e3ea11609D7dD08"
          },
          {
            "blockNumber": "75697434n",
            "newLiquidityAmount": "0n",
            "owner": "0xf31cac93488D5C687C7CbCd58e3ea11609D7dD08"
          }
        ],
        "poolId": "0x9a005a0c12cc2ef01b34e9a7f3fb91a0e6304d377b5479bd3f08f8c29cdf5deb"
      }
    ],
    [
      "38934n",
      {
        "lastOwner": "0x0380ad3322Df94334C2f30CEE24D3086FC6F3445",
        "tickLower": -232920,
        "tickUpper": -231840,
        "liquidity": "0n",
        "feeGrowthInsidePeriod0": "47497318925744163n",
        "feeGrowthInsidePeriod1": "4232319n",
        "liquidityModifications": [
          {
            "blockNumber": "75417061n",
            "newLiquidityAmount": "368133169003812n",
            "owner": "0x0380ad3322Df94334C2f30CEE24D3086FC6F3445"
          },
          {
            "blockNumber": "75443194n",
            "newLiquidityAmount": "368133169003812n",
            "owner": "0x0380ad3322Df94334C2f30CEE24D3086FC6F3445"
          },
          {
            "blockNumber": "75443201n",
            "newLiquidityAmount": "0n",
            "owner": "0x0380ad3322Df94334C2f30CEE24D3086FC6F3445"
          },
          {
            "blockNumber": "75697434n",
            "newLiquidityAmount": "0n",
            "owner": "0x0380ad3322Df94334C2f30CEE24D3086FC6F3445"
          }
        ],
        "poolId": "0x9a005a0c12cc2ef01b34e9a7f3fb91a0e6304d377b5479bd3f08f8c29cdf5deb"
      }
    ],
    [
      "39113n",
      {
        "lastOwner": "0xf31cac93488D5C687C7CbCd58e3ea11609D7dD08",
        "tickLower": -236220,
        "tickUpper": -231300,
        "liquidity": "15709624832602n",
        "feeGrowthInsidePeriod0": "1821765340102164n",
        "feeGrowthInsidePeriod1": "174717n",
        "liquidityModifications": [
          {
            "blockNumber": "75417061n",
            "newLiquidityAmount": "15709624832602n",
            "owner": "0xf31cac93488D5C687C7CbCd58e3ea11609D7dD08"
          },
          {
            "blockNumber": "75436990n",
            "newLiquidityAmount": "15709624832602n",
            "owner": "0xf31cac93488D5C687C7CbCd58e3ea11609D7dD08"
          },
          {
            "blockNumber": "75535040n",
            "newLiquidityAmount": "15709624832602n",
            "owner": "0xf31cac93488D5C687C7CbCd58e3ea11609D7dD08"
          },
          {
            "blockNumber": "75631248n",
            "newLiquidityAmount": "15709624832602n",
            "owner": "0xf31cac93488D5C687C7CbCd58e3ea11609D7dD08"
          },
          {
            "blockNumber": "75689442n",
            "newLiquidityAmount": "15709624832602n",
            "owner": "0xf31cac93488D5C687C7CbCd58e3ea11609D7dD08"
          },
          {
            "blockNumber": "75697434n",
            "newLiquidityAmount": "15709624832602n",
            "owner": "0xf31cac93488D5C687C7CbCd58e3ea11609D7dD08"
          }
        ],
        "poolId": "0x9a005a0c12cc2ef01b34e9a7f3fb91a0e6304d377b5479bd3f08f8c29cdf5deb"
      }
    ],
    [
      "39312n",
      {
        "lastOwner": "0x0380ad3322Df94334C2f30CEE24D3086FC6F3445",
        "tickLower": -232320,
        "tickUpper": -231480,
        "liquidity": "0n",
        "feeGrowthInsidePeriod0": "79087483786066803n",
        "feeGrowthInsidePeriod1": "7216293n",
        "liquidityModifications": [
          {
            "blockNumber": "75417061n",
            "newLiquidityAmount": "0n",
            "owner": "0x0000000000000000000000000000000000000000"
          },
          {
            "blockNumber": "75443409n",
            "newLiquidityAmount": "336614042484141n",
            "owner": "0x0380ad3322Df94334C2f30CEE24D3086FC6F3445"
          },
          {
            "blockNumber": "75682252n",
            "newLiquidityAmount": "336614042484141n",
            "owner": "0x0380ad3322Df94334C2f30CEE24D3086FC6F3445"
          },
          {
            "blockNumber": "75682257n",
            "newLiquidityAmount": "0n",
            "owner": "0x0380ad3322Df94334C2f30CEE24D3086FC6F3445"
          },
          {
            "blockNumber": "75697434n",
            "newLiquidityAmount": "0n",
            "owner": "0x0380ad3322Df94334C2f30CEE24D3086FC6F3445"
          }
        ],
        "poolId": "0x9a005a0c12cc2ef01b34e9a7f3fb91a0e6304d377b5479bd3f08f8c29cdf5deb"
      }
    ],
    [
      "39336n",
      {
        "lastOwner": "0x93Cf0a22a26895650A8AaE960Bf85a01ec6A551C",
        "tickLower": -234180,
        "tickUpper": -230760,
        "liquidity": "68583482448849n",
        "feeGrowthInsidePeriod0": "8046864296022819n",
        "feeGrowthInsidePeriod1": "760562n",
        "liquidityModifications": [
          {
            "blockNumber": "75417061n",
            "newLiquidityAmount": "0n",
            "owner": "0x0000000000000000000000000000000000000000"
          },
          {
            "blockNumber": "75445073n",
            "newLiquidityAmount": "68583482448849n",
            "owner": "0x93Cf0a22a26895650A8AaE960Bf85a01ec6A551C"
          },
          {
            "blockNumber": "75697434n",
            "newLiquidityAmount": "68583482448849n",
            "owner": "0x93Cf0a22a26895650A8AaE960Bf85a01ec6A551C"
          }
        ],
        "poolId": "0x9a005a0c12cc2ef01b34e9a7f3fb91a0e6304d377b5479bd3f08f8c29cdf5deb"
      }
    ],
    [
      "39384n",
      {
        "lastOwner": "0x40f81795f44b96BF88E16E055f2283B9cAEd9466",
        "tickLower": -234660,
        "tickUpper": -230820,
        "liquidity": "25929860684490n",
        "feeGrowthInsidePeriod0": "3030008400637155n",
        "feeGrowthInsidePeriod1": "280928n",
        "liquidityModifications": [
          {
            "blockNumber": "75417061n",
            "newLiquidityAmount": "0n",
            "owner": "0x0000000000000000000000000000000000000000"
          },
          {
            "blockNumber": "75450825n",
            "newLiquidityAmount": "25929860684490n",
            "owner": "0x40f81795f44b96BF88E16E055f2283B9cAEd9466"
          },
          {
            "blockNumber": "75697434n",
            "newLiquidityAmount": "25929860684490n",
            "owner": "0x40f81795f44b96BF88E16E055f2283B9cAEd9466"
          }
        ],
        "poolId": "0x9a005a0c12cc2ef01b34e9a7f3fb91a0e6304d377b5479bd3f08f8c29cdf5deb"
      }
    ],
    [
      "39415n",
      {
        "lastOwner": "0xa614A83132a2e7368aDa71dA9331817c33706770",
        "tickLower": -233100,
        "tickUpper": -230820,
        "liquidity": "23030804567022n",
        "feeGrowthInsidePeriod0": "2630336312833444n",
        "feeGrowthInsidePeriod1": "246531n",
        "liquidityModifications": [
          {
            "blockNumber": "75417061n",
            "newLiquidityAmount": "0n",
            "owner": "0x0000000000000000000000000000000000000000"
          },
          {
            "blockNumber": "75455455n",
            "newLiquidityAmount": "23030804567022n",
            "owner": "0xa614A83132a2e7368aDa71dA9331817c33706770"
          },
          {
            "blockNumber": "75697434n",
            "newLiquidityAmount": "23030804567022n",
            "owner": "0xa614A83132a2e7368aDa71dA9331817c33706770"
          }
        ],
        "poolId": "0x9a005a0c12cc2ef01b34e9a7f3fb91a0e6304d377b5479bd3f08f8c29cdf5deb"
      }
    ],
    [
      "39980n",
      {
        "lastOwner": "0xC510e6E89918F84E28D3010959c6bf016154470d",
        "tickLower": -237960,
        "tickUpper": -230220,
        "liquidity": "10640413875621n",
        "feeGrowthInsidePeriod0": "651035480461184n",
        "feeGrowthInsidePeriod1": "62114n",
        "liquidityModifications": [
          {
            "blockNumber": "75417061n",
            "newLiquidityAmount": "0n",
            "owner": "0x0000000000000000000000000000000000000000"
          },
          {
            "blockNumber": "75560294n",
            "newLiquidityAmount": "10640413875621n",
            "owner": "0xC510e6E89918F84E28D3010959c6bf016154470d"
          },
          {
            "blockNumber": "75697434n",
            "newLiquidityAmount": "10640413875621n",
            "owner": "0xC510e6E89918F84E28D3010959c6bf016154470d"
          }
        ],
        "poolId": "0x9a005a0c12cc2ef01b34e9a7f3fb91a0e6304d377b5479bd3f08f8c29cdf5deb"
      }
    ],
    [
      "40028n",
      {
        "lastOwner": "0x0AB4F882E219A33fcE9252b6213aD1146d4354d9",
        "tickLower": -238920,
        "tickUpper": -230280,
        "liquidity": "12139216035034n",
        "feeGrowthInsidePeriod0": "737220270897661n",
        "feeGrowthInsidePeriod1": "70209n",
        "liquidityModifications": [
          {
            "blockNumber": "75417061n",
            "newLiquidityAmount": "0n",
            "owner": "0x0000000000000000000000000000000000000000"
          },
          {
            "blockNumber": "75567373n",
            "newLiquidityAmount": "10503964242515n",
            "owner": "0x0AB4F882E219A33fcE9252b6213aD1146d4354d9"
          },
          {
            "blockNumber": "75567526n",
            "newLiquidityAmount": "12139216035034n",
            "owner": "0x0AB4F882E219A33fcE9252b6213aD1146d4354d9"
          },
          {
            "blockNumber": "75697434n",
            "newLiquidityAmount": "12139216035034n",
            "owner": "0x0AB4F882E219A33fcE9252b6213aD1146d4354d9"
          }
        ],
        "poolId": "0x9a005a0c12cc2ef01b34e9a7f3fb91a0e6304d377b5479bd3f08f8c29cdf5deb"
      }
    ],
    [
      "40122n",
      {
        "lastOwner": "0xB4a82f35be17A0a634F74F07Bf6074A58bA17693",
        "tickLower": -232140,
        "tickUpper": -230940,
        "liquidity": "4645533420736n",
        "feeGrowthInsidePeriod0": "274349179878292n",
        "feeGrowthInsidePeriod1": "26166n",
        "liquidityModifications": [
          {
            "blockNumber": "75417061n",
            "newLiquidityAmount": "0n",
            "owner": "0x0000000000000000000000000000000000000000"
          },
          {
            "blockNumber": "75584387n",
            "newLiquidityAmount": "4645533420736n",
            "owner": "0xB4a82f35be17A0a634F74F07Bf6074A58bA17693"
          },
          {
            "blockNumber": "75697434n",
            "newLiquidityAmount": "4645533420736n",
            "owner": "0xB4a82f35be17A0a634F74F07Bf6074A58bA17693"
          }
        ],
        "poolId": "0x9a005a0c12cc2ef01b34e9a7f3fb91a0e6304d377b5479bd3f08f8c29cdf5deb"
      }
    ],
    [
      "40214n",
      {
        "lastOwner": "0x2fe6f7c52EccC8Fea03289EC10213033a7c364b7",
        "tickLower": -231660,
        "tickUpper": -231600,
        "liquidity": "0n",
        "feeGrowthInsidePeriod0": "1765820052716n",
        "feeGrowthInsidePeriod1": "2943n",
        "liquidityModifications": [
          {
            "blockNumber": "75417061n",
            "newLiquidityAmount": "0n",
            "owner": "0x0000000000000000000000000000000000000000"
          },
          {
            "blockNumber": "75605005n",
            "newLiquidityAmount": "411902597223869n",
            "owner": "0x2fe6f7c52EccC8Fea03289EC10213033a7c364b7"
          },
          {
            "blockNumber": "75605053n",
            "newLiquidityAmount": "411902597223869n",
            "owner": "0x2fe6f7c52EccC8Fea03289EC10213033a7c364b7"
          },
          {
            "blockNumber": "75605064n",
            "newLiquidityAmount": "615050664604633n",
            "owner": "0x2fe6f7c52EccC8Fea03289EC10213033a7c364b7"
          },
          {
            "blockNumber": "75605104n",
            "newLiquidityAmount": "644462877720514n",
            "owner": "0x2fe6f7c52EccC8Fea03289EC10213033a7c364b7"
          },
          {
            "blockNumber": "75606198n",
            "newLiquidityAmount": "0n",
            "owner": "0x2fe6f7c52EccC8Fea03289EC10213033a7c364b7"
          },
          {
            "blockNumber": "75697434n",
            "newLiquidityAmount": "0n",
            "owner": "0x2fe6f7c52EccC8Fea03289EC10213033a7c364b7"
          }
        ],
        "poolId": "0x9a005a0c12cc2ef01b34e9a7f3fb91a0e6304d377b5479bd3f08f8c29cdf5deb"
      }
    ],
    [
      "40236n",
      {
        "lastOwner": "0x2fe6f7c52EccC8Fea03289EC10213033a7c364b7",
        "tickLower": -231600,
        "tickUpper": -231480,
        "liquidity": "0n",
        "feeGrowthInsidePeriod0": "57126705601654833n",
        "feeGrowthInsidePeriod1": "5655181n",
        "liquidityModifications": [
          {
            "blockNumber": "75417061n",
            "newLiquidityAmount": "0n",
            "owner": "0x0000000000000000000000000000000000000000"
          },
          {
            "blockNumber": "75606258n",
            "newLiquidityAmount": "320625991489739n",
            "owner": "0x2fe6f7c52EccC8Fea03289EC10213033a7c364b7"
          },
          {
            "blockNumber": "75607627n",
            "newLiquidityAmount": "0n",
            "owner": "0x2fe6f7c52EccC8Fea03289EC10213033a7c364b7"
          },
          {
            "blockNumber": "75607832n",
            "newLiquidityAmount": "147567874916157n",
            "owner": "0x2fe6f7c52EccC8Fea03289EC10213033a7c364b7"
          },
          {
            "blockNumber": "75608580n",
            "newLiquidityAmount": "147567874916157n",
            "owner": "0x2fe6f7c52EccC8Fea03289EC10213033a7c364b7"
          },
          {
            "blockNumber": "75608590n",
            "newLiquidityAmount": "311511552198069n",
            "owner": "0x2fe6f7c52EccC8Fea03289EC10213033a7c364b7"
          },
          {
            "blockNumber": "75608634n",
            "newLiquidityAmount": "320918326760188n",
            "owner": "0x2fe6f7c52EccC8Fea03289EC10213033a7c364b7"
          },
          {
            "blockNumber": "75609340n",
            "newLiquidityAmount": "320918326760188n",
            "owner": "0x2fe6f7c52EccC8Fea03289EC10213033a7c364b7"
          },
          {
            "blockNumber": "75609464n",
            "newLiquidityAmount": "320918326760188n",
            "owner": "0x2fe6f7c52EccC8Fea03289EC10213033a7c364b7"
          },
          {
            "blockNumber": "75609472n",
            "newLiquidityAmount": "1625097505031436n",
            "owner": "0x2fe6f7c52EccC8Fea03289EC10213033a7c364b7"
          },
          {
            "blockNumber": "75609504n",
            "newLiquidityAmount": "1625097505031436n",
            "owner": "0x2fe6f7c52EccC8Fea03289EC10213033a7c364b7"
          },
          {
            "blockNumber": "75609513n",
            "newLiquidityAmount": "1638339883722272n",
            "owner": "0x2fe6f7c52EccC8Fea03289EC10213033a7c364b7"
          },
          {
            "blockNumber": "75610632n",
            "newLiquidityAmount": "1638339883722272n",
            "owner": "0x2fe6f7c52EccC8Fea03289EC10213033a7c364b7"
          },
          {
            "blockNumber": "75610640n",
            "newLiquidityAmount": "1650884400069072n",
            "owner": "0x2fe6f7c52EccC8Fea03289EC10213033a7c364b7"
          },
          {
            "blockNumber": "75616512n",
            "newLiquidityAmount": "1650884400069072n",
            "owner": "0x2fe6f7c52EccC8Fea03289EC10213033a7c364b7"
          },
          {
            "blockNumber": "75620732n",
            "newLiquidityAmount": "1650884400069072n",
            "owner": "0x2fe6f7c52EccC8Fea03289EC10213033a7c364b7"
          },
          {
            "blockNumber": "75633892n",
            "newLiquidityAmount": "1650884400069072n",
            "owner": "0x2fe6f7c52EccC8Fea03289EC10213033a7c364b7"
          },
          {
            "blockNumber": "75634936n",
            "newLiquidityAmount": "1650884400069072n",
            "owner": "0x2fe6f7c52EccC8Fea03289EC10213033a7c364b7"
          },
          {
            "blockNumber": "75634944n",
            "newLiquidityAmount": "0n",
            "owner": "0x2fe6f7c52EccC8Fea03289EC10213033a7c364b7"
          },
          {
            "blockNumber": "75641018n",
            "newLiquidityAmount": "9775562398474n",
            "owner": "0x2fe6f7c52EccC8Fea03289EC10213033a7c364b7"
          },
          {
            "blockNumber": "75641212n",
            "newLiquidityAmount": "143391015566219n",
            "owner": "0x2fe6f7c52EccC8Fea03289EC10213033a7c364b7"
          },
          {
            "blockNumber": "75641292n",
            "newLiquidityAmount": "406124747817303n",
            "owner": "0x2fe6f7c52EccC8Fea03289EC10213033a7c364b7"
          },
          {
            "blockNumber": "75641515n",
            "newLiquidityAmount": "419946286154390n",
            "owner": "0x2fe6f7c52EccC8Fea03289EC10213033a7c364b7"
          },
          {
            "blockNumber": "75647377n",
            "newLiquidityAmount": "419946286154390n",
            "owner": "0x2fe6f7c52EccC8Fea03289EC10213033a7c364b7"
          },
          {
            "blockNumber": "75648260n",
            "newLiquidityAmount": "0n",
            "owner": "0x2fe6f7c52EccC8Fea03289EC10213033a7c364b7"
          },
          {
            "blockNumber": "75697434n",
            "newLiquidityAmount": "0n",
            "owner": "0x2fe6f7c52EccC8Fea03289EC10213033a7c364b7"
          }
        ],
        "poolId": "0x9a005a0c12cc2ef01b34e9a7f3fb91a0e6304d377b5479bd3f08f8c29cdf5deb"
      }
    ],
    [
      "40249n",
      {
        "lastOwner": "0x2fe6f7c52EccC8Fea03289EC10213033a7c364b7",
        "tickLower": -231480,
        "tickUpper": -231360,
        "liquidity": "0n",
        "feeGrowthInsidePeriod0": "0n",
        "feeGrowthInsidePeriod1": "0n",
        "liquidityModifications": [
          {
            "blockNumber": "75417061n",
            "newLiquidityAmount": "0n",
            "owner": "0x0000000000000000000000000000000000000000"
          },
          {
            "blockNumber": "75607693n",
            "newLiquidityAmount": "162029099080180n",
            "owner": "0x2fe6f7c52EccC8Fea03289EC10213033a7c364b7"
          },
          {
            "blockNumber": "75607853n",
            "newLiquidityAmount": "174851153007807n",
            "owner": "0x2fe6f7c52EccC8Fea03289EC10213033a7c364b7"
          },
          {
            "blockNumber": "75608548n",
            "newLiquidityAmount": "0n",
            "owner": "0x2fe6f7c52EccC8Fea03289EC10213033a7c364b7"
          },
          {
            "blockNumber": "75697434n",
            "newLiquidityAmount": "0n",
            "owner": "0x2fe6f7c52EccC8Fea03289EC10213033a7c364b7"
          }
        ],
        "poolId": "0x9a005a0c12cc2ef01b34e9a7f3fb91a0e6304d377b5479bd3f08f8c29cdf5deb"
      }
    ],
    [
      "40355n",
      {
        "lastOwner": "0xf31cac93488D5C687C7CbCd58e3ea11609D7dD08",
        "tickLower": -233100,
        "tickUpper": -231240,
        "liquidity": "37215661395302n",
        "feeGrowthInsidePeriod0": "1072021977544636n",
        "feeGrowthInsidePeriod1": "102918n",
        "liquidityModifications": [
          {
            "blockNumber": "75417061n",
            "newLiquidityAmount": "0n",
            "owner": "0x0000000000000000000000000000000000000000"
          },
          {
            "blockNumber": "75631488n",
            "newLiquidityAmount": "37215661395302n",
            "owner": "0xf31cac93488D5C687C7CbCd58e3ea11609D7dD08"
          },
          {
            "blockNumber": "75689422n",
            "newLiquidityAmount": "37215661395302n",
            "owner": "0xf31cac93488D5C687C7CbCd58e3ea11609D7dD08"
          },
          {
            "blockNumber": "75697434n",
            "newLiquidityAmount": "37215661395302n",
            "owner": "0xf31cac93488D5C687C7CbCd58e3ea11609D7dD08"
          }
        ],
        "poolId": "0x9a005a0c12cc2ef01b34e9a7f3fb91a0e6304d377b5479bd3f08f8c29cdf5deb"
      }
    ],
    [
      "40375n",
      {
        "lastOwner": "0x2fe6f7c52EccC8Fea03289EC10213033a7c364b7",
        "tickLower": -231480,
        "tickUpper": -231360,
        "liquidity": "4456642847816383n",
        "feeGrowthInsidePeriod0": "11884352914221108n",
        "feeGrowthInsidePeriod1": "2183346n",
        "liquidityModifications": [
          {
            "blockNumber": "75417061n",
            "newLiquidityAmount": "0n",
            "owner": "0x0000000000000000000000000000000000000000"
          },
          {
            "blockNumber": "75635031n",
            "newLiquidityAmount": "328994351858497n",
            "owner": "0x2fe6f7c52EccC8Fea03289EC10213033a7c364b7"
          },
          {
            "blockNumber": "75635084n",
            "newLiquidityAmount": "328994351858497n",
            "owner": "0x2fe6f7c52EccC8Fea03289EC10213033a7c364b7"
          },
          {
            "blockNumber": "75635089n",
            "newLiquidityAmount": "1160020909376694n",
            "owner": "0x2fe6f7c52EccC8Fea03289EC10213033a7c364b7"
          },
          {
            "blockNumber": "75635114n",
            "newLiquidityAmount": "1160020909376694n",
            "owner": "0x2fe6f7c52EccC8Fea03289EC10213033a7c364b7"
          },
          {
            "blockNumber": "75635121n",
            "newLiquidityAmount": "1497064395582453n",
            "owner": "0x2fe6f7c52EccC8Fea03289EC10213033a7c364b7"
          },
          {
            "blockNumber": "75635152n",
            "newLiquidityAmount": "1497064395582453n",
            "owner": "0x2fe6f7c52EccC8Fea03289EC10213033a7c364b7"
          },
          {
            "blockNumber": "75635158n",
            "newLiquidityAmount": "1600793186527251n",
            "owner": "0x2fe6f7c52EccC8Fea03289EC10213033a7c364b7"
          },
          {
            "blockNumber": "75635187n",
            "newLiquidityAmount": "1629862330497471n",
            "owner": "0x2fe6f7c52EccC8Fea03289EC10213033a7c364b7"
          },
          {
            "blockNumber": "75640990n",
            "newLiquidityAmount": "1629862330497471n",
            "owner": "0x2fe6f7c52EccC8Fea03289EC10213033a7c364b7"
          },
          {
            "blockNumber": "75641173n",
            "newLiquidityAmount": "1222396747873104n",
            "owner": "0x2fe6f7c52EccC8Fea03289EC10213033a7c364b7"
          },
          {
            "blockNumber": "75647362n",
            "newLiquidityAmount": "1222396747873104n",
            "owner": "0x2fe6f7c52EccC8Fea03289EC10213033a7c364b7"
          },
          {
            "blockNumber": "75649693n",
            "newLiquidityAmount": "0n",
            "owner": "0x2fe6f7c52EccC8Fea03289EC10213033a7c364b7"
          },
          {
            "blockNumber": "75655460n",
            "newLiquidityAmount": "1630021960937692n",
            "owner": "0x2fe6f7c52EccC8Fea03289EC10213033a7c364b7"
          },
          {
            "blockNumber": "75665682n",
            "newLiquidityAmount": "1630021960937692n",
            "owner": "0x2fe6f7c52EccC8Fea03289EC10213033a7c364b7"
          },
          {
            "blockNumber": "75665692n",
            "newLiquidityAmount": "2901158709238035n",
            "owner": "0x2fe6f7c52EccC8Fea03289EC10213033a7c364b7"
          },
          {
            "blockNumber": "75665738n",
            "newLiquidityAmount": "2901158709238035n",
            "owner": "0x2fe6f7c52EccC8Fea03289EC10213033a7c364b7"
          },
          {
            "blockNumber": "75665745n",
            "newLiquidityAmount": "3023169871894102n",
            "owner": "0x2fe6f7c52EccC8Fea03289EC10213033a7c364b7"
          },
          {
            "blockNumber": "75675528n",
            "newLiquidityAmount": "3023169871894102n",
            "owner": "0x2fe6f7c52EccC8Fea03289EC10213033a7c364b7"
          },
          {
            "blockNumber": "75675535n",
            "newLiquidityAmount": "3582653119595030n",
            "owner": "0x2fe6f7c52EccC8Fea03289EC10213033a7c364b7"
          },
          {
            "blockNumber": "75675560n",
            "newLiquidityAmount": "3582653119595030n",
            "owner": "0x2fe6f7c52EccC8Fea03289EC10213033a7c364b7"
          },
          {
            "blockNumber": "75675567n",
            "newLiquidityAmount": "4385304639512604n",
            "owner": "0x2fe6f7c52EccC8Fea03289EC10213033a7c364b7"
          },
          {
            "blockNumber": "75675590n",
            "newLiquidityAmount": "4385304639512604n",
            "owner": "0x2fe6f7c52EccC8Fea03289EC10213033a7c364b7"
          },
          {
            "blockNumber": "75675596n",
            "newLiquidityAmount": "4509236558154609n",
            "owner": "0x2fe6f7c52EccC8Fea03289EC10213033a7c364b7"
          },
          {
            "blockNumber": "75677598n",
            "newLiquidityAmount": "4509236558154609n",
            "owner": "0x2fe6f7c52EccC8Fea03289EC10213033a7c364b7"
          },
          {
            "blockNumber": "75677606n",
            "newLiquidityAmount": "4548038418206656n",
            "owner": "0x2fe6f7c52EccC8Fea03289EC10213033a7c364b7"
          },
          {
            "blockNumber": "75685280n",
            "newLiquidityAmount": "4548038418206656n",
            "owner": "0x2fe6f7c52EccC8Fea03289EC10213033a7c364b7"
          },
          {
            "blockNumber": "75685460n",
            "newLiquidityAmount": "0n",
            "owner": "0x2fe6f7c52EccC8Fea03289EC10213033a7c364b7"
          },
          {
            "blockNumber": "75690964n",
            "newLiquidityAmount": "11441131941016n",
            "owner": "0x2fe6f7c52EccC8Fea03289EC10213033a7c364b7"
          },
          {
            "blockNumber": "75691822n",
            "newLiquidityAmount": "98655677324118n",
            "owner": "0x2fe6f7c52EccC8Fea03289EC10213033a7c364b7"
          },
          {
            "blockNumber": "75691871n",
            "newLiquidityAmount": "305689888090359n",
            "owner": "0x2fe6f7c52EccC8Fea03289EC10213033a7c364b7"
          },
          {
            "blockNumber": "75692339n",
            "newLiquidityAmount": "305689888090359n",
            "owner": "0x2fe6f7c52EccC8Fea03289EC10213033a7c364b7"
          },
          {
            "blockNumber": "75692346n",
            "newLiquidityAmount": "912147323429079n",
            "owner": "0x2fe6f7c52EccC8Fea03289EC10213033a7c364b7"
          },
          {
            "blockNumber": "75692367n",
            "newLiquidityAmount": "912147323429079n",
            "owner": "0x2fe6f7c52EccC8Fea03289EC10213033a7c364b7"
          },
          {
            "blockNumber": "75692372n",
            "newLiquidityAmount": "1648655970228213n",
            "owner": "0x2fe6f7c52EccC8Fea03289EC10213033a7c364b7"
          },
          {
            "blockNumber": "75692407n",
            "newLiquidityAmount": "1648655970228213n",
            "owner": "0x2fe6f7c52EccC8Fea03289EC10213033a7c364b7"
          },
          {
            "blockNumber": "75692412n",
            "newLiquidityAmount": "3152268966416842n",
            "owner": "0x2fe6f7c52EccC8Fea03289EC10213033a7c364b7"
          },
          {
            "blockNumber": "75693701n",
            "newLiquidityAmount": "3152268966416842n",
            "owner": "0x2fe6f7c52EccC8Fea03289EC10213033a7c364b7"
          },
          {
            "blockNumber": "75693709n",
            "newLiquidityAmount": "4355635838955136n",
            "owner": "0x2fe6f7c52EccC8Fea03289EC10213033a7c364b7"
          },
          {
            "blockNumber": "75696448n",
            "newLiquidityAmount": "4355635838955136n",
            "owner": "0x2fe6f7c52EccC8Fea03289EC10213033a7c364b7"
          },
          {
            "blockNumber": "75696462n",
            "newLiquidityAmount": "4456642847816383n",
            "owner": "0x2fe6f7c52EccC8Fea03289EC10213033a7c364b7"
          },
          {
            "blockNumber": "75697434n",
            "newLiquidityAmount": "4456642847816383n",
            "owner": "0x2fe6f7c52EccC8Fea03289EC10213033a7c364b7"
          }
        ],
        "poolId": "0x9a005a0c12cc2ef01b34e9a7f3fb91a0e6304d377b5479bd3f08f8c29cdf5deb"
      }
    ],
    [
      "40472n",
      {
        "lastOwner": "0x2fe6f7c52EccC8Fea03289EC10213033a7c364b7",
        "tickLower": -231480,
        "tickUpper": -231240,
        "liquidity": "0n",
        "feeGrowthInsidePeriod0": "5484759751868118n",
        "feeGrowthInsidePeriod1": "212444n",
        "liquidityModifications": [
          {
            "blockNumber": "75417061n",
            "newLiquidityAmount": "0n",
            "owner": "0x0000000000000000000000000000000000000000"
          },
          {
            "blockNumber": "75649886n",
            "newLiquidityAmount": "817455883832783n",
            "owner": "0x2fe6f7c52EccC8Fea03289EC10213033a7c364b7"
          },
          {
            "blockNumber": "75654952n",
            "newLiquidityAmount": "817455883832783n",
            "owner": "0x2fe6f7c52EccC8Fea03289EC10213033a7c364b7"
          },
          {
            "blockNumber": "75655410n",
            "newLiquidityAmount": "0n",
            "owner": "0x2fe6f7c52EccC8Fea03289EC10213033a7c364b7"
          },
          {
            "blockNumber": "75697434n",
            "newLiquidityAmount": "0n",
            "owner": "0x2fe6f7c52EccC8Fea03289EC10213033a7c364b7"
          }
        ],
        "poolId": "0x9a005a0c12cc2ef01b34e9a7f3fb91a0e6304d377b5479bd3f08f8c29cdf5deb"
      }
    ],
    [
      "40648n",
      {
        "lastOwner": "0x0380ad3322Df94334C2f30CEE24D3086FC6F3445",
        "tickLower": -231720,
        "tickUpper": -230760,
        "liquidity": "548156607985672n",
        "feeGrowthInsidePeriod0": "4719372479433628n",
        "feeGrowthInsidePeriod1": "254367n",
        "liquidityModifications": [
          {
            "blockNumber": "75417061n",
            "newLiquidityAmount": "0n",
            "owner": "0x0000000000000000000000000000000000000000"
          },
          {
            "blockNumber": "75682548n",
            "newLiquidityAmount": "535578878990202n",
            "owner": "0x0380ad3322Df94334C2f30CEE24D3086FC6F3445"
          },
          {
            "blockNumber": "75692410n",
            "newLiquidityAmount": "548156607985672n",
            "owner": "0x0380ad3322Df94334C2f30CEE24D3086FC6F3445"
          },
          {
            "blockNumber": "75697434n",
            "newLiquidityAmount": "548156607985672n",
            "owner": "0x0380ad3322Df94334C2f30CEE24D3086FC6F3445"
          }
        ],
        "poolId": "0x9a005a0c12cc2ef01b34e9a7f3fb91a0e6304d377b5479bd3f08f8c29cdf5deb"
      }
    ],
    [
      "40664n",
      {
        "lastOwner": "0x2fe6f7c52EccC8Fea03289EC10213033a7c364b7",
        "tickLower": -231300,
        "tickUpper": -231180,
        "liquidity": "0n",
        "feeGrowthInsidePeriod0": "7222185750315053n",
        "feeGrowthInsidePeriod1": "70428n",
        "liquidityModifications": [
          {
            "blockNumber": "75417061n",
            "newLiquidityAmount": "0n",
            "owner": "0x0000000000000000000000000000000000000000"
          },
          {
            "blockNumber": "75685536n",
            "newLiquidityAmount": "7867702142967n",
            "owner": "0x2fe6f7c52EccC8Fea03289EC10213033a7c364b7"
          },
          {
            "blockNumber": "75685739n",
            "newLiquidityAmount": "1373485448800031n",
            "owner": "0x2fe6f7c52EccC8Fea03289EC10213033a7c364b7"
          },
          {
            "blockNumber": "75686101n",
            "newLiquidityAmount": "1373485448800031n",
            "owner": "0x2fe6f7c52EccC8Fea03289EC10213033a7c364b7"
          },
          {
            "blockNumber": "75686109n",
            "newLiquidityAmount": "2203852137462546n",
            "owner": "0x2fe6f7c52EccC8Fea03289EC10213033a7c364b7"
          },
          {
            "blockNumber": "75687718n",
            "newLiquidityAmount": "2203852137462546n",
            "owner": "0x2fe6f7c52EccC8Fea03289EC10213033a7c364b7"
          },
          {
            "blockNumber": "75687884n",
            "newLiquidityAmount": "2203852137462546n",
            "owner": "0x2fe6f7c52EccC8Fea03289EC10213033a7c364b7"
          },
          {
            "blockNumber": "75687904n",
            "newLiquidityAmount": "4502199845744427n",
            "owner": "0x2fe6f7c52EccC8Fea03289EC10213033a7c364b7"
          },
          {
            "blockNumber": "75690899n",
            "newLiquidityAmount": "4502199845744427n",
            "owner": "0x2fe6f7c52EccC8Fea03289EC10213033a7c364b7"
          },
          {
            "blockNumber": "75690909n",
            "newLiquidityAmount": "0n",
            "owner": "0x2fe6f7c52EccC8Fea03289EC10213033a7c364b7"
          },
          {
            "blockNumber": "75697434n",
            "newLiquidityAmount": "0n",
            "owner": "0x2fe6f7c52EccC8Fea03289EC10213033a7c364b7"
          }
        ],
        "poolId": "0x9a005a0c12cc2ef01b34e9a7f3fb91a0e6304d377b5479bd3f08f8c29cdf5deb"
      }
    ]
  ],
  "lpData": [
    [
      "0xa2DFeb674d997b68ec5adB0A6fb9136BD45C2D2d",
      {
        "periodFeesCurrency0": "0n",
        "periodFeesCurrency1": "0n",
        "totalFeesCommonDenominator": "0n",
        "reward": "0n"
      }
    ],
    [
      "0x40f81795f44b96BF88E16E055f2283B9cAEd9466",
      {
        "periodFeesCurrency0": "55556940300533264n",
        "periodFeesCurrency1": "2397574n",
        "totalFeesCommonDenominator": "7701614n",
        "reward": "4783702n"
      }
    ],
    [
      "0xEf2CD02960bd303C000C48C6ea95f651CfB83205",
      {
        "periodFeesCurrency0": "1502685868172247n",
        "periodFeesCurrency1": "143461n",
        "totalFeesCommonDenominator": "286922n",
        "reward": "178215n"
      }
    ],
    [
      "0xCDA0c8a5f22565ae0efB889E5dBb6CE60498d0b4",
      {
        "periodFeesCurrency0": "0n",
        "periodFeesCurrency1": "0n",
        "totalFeesCommonDenominator": "0n",
        "reward": "0n"
      }
    ],
    [
      "0x5196E6ff6b95536874ba6405c11f465e026099e0",
      {
        "periodFeesCurrency0": "117683550899n",
        "periodFeesCurrency1": "11n",
        "totalFeesCommonDenominator": "22n",
        "reward": "13n"
      }
    ],
    [
      "0x93Cf0a22a26895650A8AaE960Bf85a01ec6A551C",
      {
        "periodFeesCurrency0": "15451100508846828n",
        "periodFeesCurrency1": "1379690n",
        "totalFeesCommonDenominator": "2854811n",
        "reward": "1773208n"
      }
    ],
    [
      "0x0AB4F882E219A33fcE9252b6213aD1146d4354d9",
      {
        "periodFeesCurrency0": "56682295960172344n",
        "periodFeesCurrency1": "3426527n",
        "totalFeesCommonDenominator": "8838005n",
        "reward": "5489549n"
      }
    ],
    [
      "0xa614A83132a2e7368aDa71dA9331817c33706770",
      {
        "periodFeesCurrency0": "2830287984569954n",
        "periodFeesCurrency1": "267337n",
        "totalFeesCommonDenominator": "537545n",
        "reward": "333885n"
      }
    ],
    [
      "0xabF76381Ab5538598AA4cd77d01De16c3F48a54A",
      {
        "periodFeesCurrency0": "490046405776458n",
        "periodFeesCurrency1": "46784n",
        "totalFeesCommonDenominator": "93568n",
        "reward": "58117n"
      }
    ],
    [
      "0xD98b537374623B2cFc2f083fcE50b525A697A6b7",
      {
        "periodFeesCurrency0": "158201094047744899n",
        "periodFeesCurrency1": "15103512n",
        "totalFeesCommonDenominator": "30207024n",
        "reward": "18762486n"
      }
    ],
    [
      "0xBa2ACC7b677dd133F8B6e5cEde8ea7Fd9C1c6795",
      {
        "periodFeesCurrency0": "15694476985398140n",
        "periodFeesCurrency1": "1498357n",
        "totalFeesCommonDenominator": "2996714n",
        "reward": "1861348n"
      }
    ],
    [
      "0xca279F34640B8E3232aBD83951169Be9414CDfda",
      {
        "periodFeesCurrency0": "29312573653884611n",
        "periodFeesCurrency1": "2799365n",
        "totalFeesCommonDenominator": "5597846n",
        "reward": "3476989n"
      }
    ],
    [
      "0xD12eabdDA283287cBe21EB1DaAdff5110B44be03",
      {
        "periodFeesCurrency0": "21773270927932099n",
        "periodFeesCurrency1": "2078701n",
        "totalFeesCommonDenominator": "4157402n",
        "reward": "2582286n"
      }
    ],
    [
      "0xf31cac93488D5C687C7CbCd58e3ea11609D7dD08",
      {
        "periodFeesCurrency0": "3823714505716246n",
        "periodFeesCurrency1": "371910n",
        "totalFeesCommonDenominator": "736961n",
        "reward": "457748n"
      }
    ],
    [
      "0x0380ad3322Df94334C2f30CEE24D3086FC6F3445",
      {
        "periodFeesCurrency0": "131304175191244594n",
        "periodFeesCurrency1": "11702979n",
        "totalFeesCommonDenominator": "24238633n",
        "reward": "15055340n"
      }
    ],
    [
      "0xC510e6E89918F84E28D3010959c6bf016154470d",
      {
        "periodFeesCurrency0": "651035480461184n",
        "periodFeesCurrency1": "62114n",
        "totalFeesCommonDenominator": "124268n",
        "reward": "77186n"
      }
    ],
    [
      "0xB4a82f35be17A0a634F74F07Bf6074A58bA17693",
      {
        "periodFeesCurrency0": "274349179878292n",
        "periodFeesCurrency1": "26166n",
        "totalFeesCommonDenominator": "52358n",
        "reward": "32521n"
      }
    ],
    [
      "0x2fe6f7c52EccC8Fea03289EC10213033a7c364b7",
      {
        "periodFeesCurrency0": "81719769838111828n",
        "periodFeesCurrency1": "8124342n",
        "totalFeesCommonDenominator": "15926156n",
        "reward": "9892212n"
      }
    ]
  ]
}